{
  "custom": {},
  "params": {},
  "props": {
    "defaultSize": {
      "height": 700,
      "width": 950
    }
  },
  "root": {
    "children": [
      {
        "children": [
          {
            "meta": {
              "name": "Spacer"
            },
            "position": {
              "basis": "12px"
            },
            "props": {
              "style": {
                "classes": "Pages/Main",
                "color": "#FEFAFA",
                "fontSize": "28px",
                "fontWeight": "bold",
                "lineHeight": "3",
                "textAlign": "center",
                "textIndent": "-50px"
              }
            },
            "type": "ia.display.label"
          },
          {
            "meta": {
              "name": "Icon_Back"
            },
            "position": {
              "basis": "50px"
            },
            "props": {
              "color": "#FFFFFF",
              "path": "material/arrow_back_ios_",
              "style": {
                "classes": "Pages/Main"
              }
            },
            "type": "ia.display.icon"
          },
          {
            "meta": {
              "name": "Label"
            },
            "position": {
              "basis": "950px",
              "grow": 1
            },
            "props": {
              "alignVertical": "center",
              "style": {
                "classes": "Pages/Main",
                "color": "#FEFAFA",
                "fontSize": "28px",
                "fontWeight": "bold",
                "lineHeight": 1,
                "textAlign": "center",
                "textIndent": "-50px"
              },
              "text": "Seleccionar Planta"
            },
            "type": "ia.display.label"
          }
        ],
        "meta": {
          "name": "FlexContainer"
        },
        "position": {
          "basis": "100px"
        },
        "type": "ia.container.flex"
      },
      {
        "meta": {
          "name": "Label"
        },
        "position": {
          "basis": "20%"
        },
        "type": "ia.display.label"
      },
      {
        "children": [
          {
            "meta": {
              "name": "Spacer"
            },
            "position": {
              "basis": "10%"
            },
            "type": "ia.display.label"
          },
          {
            "events": {
              "component": {
                "onActionPerformed": {
                  "config": {
                    "params": {
                      "planta": "1100_"
                    },
                    "view": "Planning/Navigation/AreaSelection"
                  },
                  "scope": "C",
                  "type": "nav"
                }
              }
            },
            "meta": {
              "name": "Button_1100"
            },
            "position": {
              "basis": "50px",
              "grow": 1
            },
            "props": {
              "image": {
                "height": "22%",
                "source": "/system/images/Icons/minipak-logo.png",
                "width": "90%"
              },
              "style": {
                "backgroundColor": "#F6F6F6"
              },
              "text": ""
            },
            "type": "ia.input.button"
          },
          {
            "meta": {
              "name": "Spacer_1"
            },
            "position": {
              "basis": "10%"
            },
            "type": "ia.display.label"
          },
          {
            "events": {
              "component": {
                "onActionPerformed": {
                  "config": {
                    "params": {
                      "planta": "2100_"
                    },
                    "view": "Planning/Navigation/AreaSelection"
                  },
                  "scope": "C",
                  "type": "nav"
                }
              }
            },
            "meta": {
              "name": "Button_2100"
            },
            "position": {
              "basis": "50px",
              "grow": 1
            },
            "props": {
              "image": {
                "height": "22%",
                "source": "/system/images/Icons/polybol-logo.png",
                "width": "90%"
              },
              "style": {
                "backgroundColor": "#F6F6F6"
              },
              "text": ""
            },
            "type": "ia.input.button"
          },
          {
            "meta": {
              "name": "Spacer_0"
            },
            "position": {
              "basis": "10%"
            },
            "type": "ia.display.label"
          }
        ],
        "meta": {
          "name": "FlexContainer_0"
        },
        "position": {
          "basis": "614px"
        },
        "type": "ia.container.flex"
      },
      {
        "meta": {
          "name": "Label_0"
        },
        "position": {
          "basis": "20%"
        },
        "type": "ia.display.label"
      }
    ],
    "meta": {
      "name": "root"
    },
    "props": {
      "direction": "column"
    },
    "type": "ia.container.flex"
  }
}